copyer/__init__.py
copyer/feature_extraction/__init__.py
copyer/feature_extraction/categorical.py
copyer/geo/__init__.py
copyer/geo/geopop.py
copyer/geo/gutil.py
copyer/seq/__init__.py
copyer/seq/binary_sequence_makers.py
copyer/seq/event_extractors.py
copyer/seq/window_pairs.py
copyer-0.0.1.dist-info/LICENSE
copyer-0.0.1.dist-info/METADATA
copyer-0.0.1.dist-info/WHEEL
copyer-0.0.1.dist-info/top_level.txt
copyer-0.0.1.dist-info/RECORD
